nagios_public_status_page/__init__.py
nagios_public_status_page/api/__init__.py
nagios_public_status_page/api/routes.py
nagios_public_status_page/api/schemas.py
nagios_public_status_page/collector/__init__.py
nagios_public_status_page/collector/incident_tracker.py
nagios_public_status_page/collector/poller.py
nagios_public_status_page/config.py
nagios_public_status_page/db/__init__.py
nagios_public_status_page/db/database.py
nagios_public_status_page/main.py
nagios_public_status_page/models.py
nagios_public_status_page/parser/__init__.py
nagios_public_status_page/parser/status_dat.py
nagios_public_status_page/py.typed
nagios_public_status_page/rss/__init__.py
nagios_public_status_page/rss/feed_generator.py
nagios_public_status_page-0.2.1.dist-info/WHEEL
nagios_public_status_page-0.2.1.dist-info/entry_points.txt
nagios_public_status_page-0.2.1.dist-info/METADATA
nagios_public_status_page-0.2.1.dist-info/RECORD
