Metadata-Version: 2.3
Name: nagios-public-status-page
Version: 0.2.1
Summary: A public-facing status page that displays Nagios monitoring data with incident tracking and RSS feeds
Keywords: nagios,monitoring,status-page,incidents,rss,fastapi
Author: Paul Macdonnell
Author-email: Paul Macdonnell <pgmac@pgmac.net>
License: MIT
Classifier: Development Status :: 4 - Beta
Classifier: Intended Audience :: System Administrators
Classifier: License :: OSI Approved :: MIT License
Classifier: Operating System :: OS Independent
Classifier: Programming Language :: Python :: 3
Classifier: Programming Language :: Python :: 3.13
Classifier: Topic :: System :: Monitoring
Classifier: Topic :: System :: Systems Administration
Classifier: Framework :: FastAPI
Requires-Dist: apscheduler>=3.11.2
Requires-Dist: fastapi>=0.128.0
Requires-Dist: feedgen>=1.0.0
Requires-Dist: python-multipart>=0.0.21
Requires-Dist: pyyaml>=6.0.3
Requires-Dist: sqlalchemy>=2.0.45
Requires-Dist: uvicorn>=0.40.0
Maintainer: Paul Macdonnell
Maintainer-email: Paul Macdonnell <pgmac@pgmac.net>
Requires-Python: >=3.13
Project-URL: Documentation, https://github.com/pgmac/nagios-public-status-page#readme
Project-URL: Homepage, https://github.com/pgmac/nagios-public-status-page
Project-URL: Issues, https://github.com/pgmac/nagios-public-status-page/issues
Project-URL: Repository, https://github.com/pgmac/nagios-public-status-page
